mcp_python_env_debugger/__init__.py
mcp_python_env_debugger-0.0.4.dist-info/METADATA
mcp_python_env_debugger-0.0.4.dist-info/WHEEL
mcp_python_env_debugger-0.0.4.dist-info/entry_points.txt
mcp_python_env_debugger-0.0.4.dist-info/top_level.txt
mcp_python_env_debugger-0.0.4.dist-info/RECORD
