Metadata-Version: 2.4
Name: mcp-python-env-debugger
Version: 0.0.4
Summary: Add your description here
Requires-Python: >=3.1
Requires-Dist: mcp[cli]>=1.8.1
